logaccessparse/LICENSE
logaccessparse/LICENSEAPK
logaccessparse/NOTICE.html
logaccessparse/README.MD
logaccessparse/__init__.py
logaccessparse/ac.apk
logaccessparse/requirements.txt
logaccessparse/thirdparty.json
logaccessparse-0.10.dist-info/LICENSE.rst
logaccessparse-0.10.dist-info/METADATA
logaccessparse-0.10.dist-info/WHEEL
logaccessparse-0.10.dist-info/top_level.txt
logaccessparse-0.10.dist-info/RECORD
