Metadata-Version: 2.1
Name: logaccessparse
Version: 0.10
Summary: Accessibility parser for Android
Home-page: https://github.com/hansalemaos/logaccessparse
Author: Johannes Fischer
Author-email: aulasparticularesdealemaosp@gmail.com
License: MIT
Keywords: uiautomator,events
Classifier: Development Status :: 4 - Beta
Classifier: Programming Language :: Python :: 3 :: Only
Classifier: Programming Language :: Python :: 3.10
Classifier: Topic :: Software Development :: Libraries :: Python Modules
Classifier: Topic :: Utilities
License-File: LICENSE.rst
Requires-Dist: mymulti-key-dict
